{"chunk_definitions":[{"chunk_id":"csetup_chunk","chunk_label":"setup","document_id":"86EDACFE","expansion_state":0,"options":{"engine":"r","include":false,"label":"setup"},"row":11,"row_count":1,"visible":true},{"chunk_id":"cqptjeqqlc3dc","chunk_label":"unnamed-chunk-1","document_id":"86EDACFE","expansion_state":0,"options":{"engine":"r","label":"unnamed-chunk-1"},"row":22,"row_count":1,"visible":true},{"chunk_id":"c57q7dx5x805z","chunk_label":"unnamed-chunk-2","document_id":"86EDACFE","expansion_state":0,"options":{"engine":"r","label":"unnamed-chunk-4"},"row":29,"row_count":1,"visible":true},{"chunk_id":"cy9stqwnkmynh","chunk_label":"unnamed-chunk-3","document_id":"86EDACFE","expansion_state":0,"options":{"engine":"r","label":"unnamed-chunk-5"},"row":35,"row_count":1,"visible":true},{"chunk_id":"cb4xn31ohx242","chunk_label":"unnamed-chunk-4","document_id":"86EDACFE","expansion_state":0,"options":{"engine":"r","label":"unnamed-chunk-6"},"row":40,"row_count":1,"visible":true},{"chunk_id":"cnp6mti852uw0","chunk_label":"unnamed-chunk-5","document_id":"86EDACFE","expansion_state":0,"options":{"engine":"r","label":"unnamed-chunk-7"},"row":46,"row_count":1,"visible":true},{"chunk_id":"cfumc5q3ftkex","chunk_label":"unnamed-chunk-6","document_id":"86EDACFE","expansion_state":0,"options":{"engine":"r","label":"unnamed-chunk-8"},"row":51,"row_count":1,"visible":true},{"chunk_id":"c4jt8y8foyink","chunk_label":"unnamed-chunk-7","document_id":"86EDACFE","expansion_state":0,"options":{"engine":"r","label":"unnamed-chunk-16"},"row":65,"row_count":1,"visible":true},{"chunk_id":"czgl0o0j1mv1t","chunk_label":"unnamed-chunk-8","document_id":"86EDACFE","expansion_state":0,"options":{"engine":"r","label":"unnamed-chunk-17"},"row":89,"row_count":1,"visible":true},{"chunk_id":"c6uudyjq3flht","chunk_label":"unnamed-chunk-9","document_id":"86EDACFE","expansion_state":0,"options":{"engine":"r","label":"unnamed-chunk-18"},"row":94,"row_count":1,"visible":true},{"chunk_id":"czidlxttj509b","chunk_label":"unnamed-chunk-10","document_id":"86EDACFE","expansion_state":0,"options":{"engine":"r","label":"unnamed-chunk-2"},"row":101,"row_count":1,"visible":true},{"chunk_id":"cqvwqw1gvyjqh","chunk_label":"unnamed-chunk-11","document_id":"86EDACFE","expansion_state":0,"options":{"engine":"r","label":"unnamed-chunk-3"},"row":116,"row_count":1,"visible":true},{"chunk_id":"cvs92ju986eg9","chunk_label":"unnamed-chunk-12","document_id":"86EDACFE","expansion_state":0,"options":{"engine":"r","label":"unnamed-chunk-276"},"row":132,"row_count":1,"visible":true},{"chunk_id":"csdjng2547l56","chunk_label":"unnamed-chunk-13","document_id":"86EDACFE","expansion_state":0,"options":{"engine":"r","label":"unnamed-chunk-277"},"row":152,"row_count":1,"visible":true}],"doc_write_time":1584710648}